gari/Example_GeneticAlgorithm.py
gari/__init__.py
gari-1.4.dist-info/METADATA
gari-1.4.dist-info/RECORD
gari-1.4.dist-info/WHEEL
gari-1.4.dist-info/top_level.txt
