Metadata-Version: 2.1
Name: gari
Version: 1.4
Summary: Reproducing Image using Genetic Algorithm
Home-page: https://github.com/ahmedfgad/GARI
Author: Ahmed Gad
Author-email: ahmed.f.gad@gmail.com
License: UNKNOWN
Platform: UNKNOWN
Classifier: Programming Language :: Python :: 3
Classifier: License :: OSI Approved :: MIT License
Classifier: Operating System :: OS Independent
